{
  "items": [
    {
      "base_type_id": "iron_sword",
      "name": "Warrior's Iron Sword",
      "base_name": "Iron Sword",
      "class": "one_hand_sword",
      "rarity": "magic",
      "tags": [],
      "requirements": { "level": 1, "strength": 0, "dexterity": 0, "intelligence": 0 },
      "implicit": { "affix_id": "acc_implicit", "name": "Accuracy", "stat": "increased_accuracy", "scope": "global", "tier": 1, "value": 15, "tier_min": 10, "tier_max": 20 },
      "prefixes": [
        { "affix_id": "added_phys", "name": "Heavy", "stat": "added_physical_damage", "scope": "local", "tier": 1, "value": 8, "value_max": 12, "tier_min": 8, "tier_max": 12, "tier_max_value": [8, 12] }
      ],
      "suffixes": [
        { "affix_id": "attack_speed", "name": "of Speed", "stat": "increased_attack_speed", "scope": "global", "tier": 1, "value": 8, "tier_min": 5, "tier_max": 10 }
      ],
      "defenses": { "armour": null, "evasion": null, "energy_shield": null },
      "damage": { "damages": [{ "damage_type": "physical", "min": 30, "max": 60 }], "attack_speed": 1.2, "critical_chance": 5.0, "spell_efficiency": 0.0 }
    },
    {
      "base_type_id": "steel_sword",
      "name": "Tempered Steel Sword",
      "base_name": "Steel Sword",
      "class": "one_hand_sword",
      "rarity": "rare",
      "tags": [],
      "requirements": { "level": 10, "strength": 20, "dexterity": 0, "intelligence": 0 },
      "implicit": { "affix_id": "acc_implicit", "name": "Accuracy", "stat": "increased_accuracy", "scope": "global", "tier": 2, "value": 25, "tier_min": 20, "tier_max": 30 },
      "prefixes": [
        { "affix_id": "added_phys", "name": "Cruel", "stat": "added_physical_damage", "scope": "local", "tier": 2, "value": 20, "value_max": 30, "tier_min": 20, "tier_max": 30, "tier_max_value": [20, 30] },
        { "affix_id": "inc_phys", "name": "Tyrannical", "stat": "increased_physical_damage", "scope": "local", "tier": 2, "value": 80, "tier_min": 70, "tier_max": 90 }
      ],
      "suffixes": [
        { "affix_id": "attack_speed", "name": "of Fury", "stat": "increased_attack_speed", "scope": "global", "tier": 2, "value": 15, "tier_min": 12, "tier_max": 18 },
        { "affix_id": "crit_chance", "name": "of Incision", "stat": "increased_critical_chance", "scope": "global", "tier": 1, "value": 20, "tier_min": 15, "tier_max": 25 }
      ],
      "defenses": { "armour": null, "evasion": null, "energy_shield": null },
      "damage": { "damages": [{ "damage_type": "physical", "min": 45, "max": 85 }], "attack_speed": 1.3, "critical_chance": 6.0, "spell_efficiency": 0.0 }
    },
    {
      "base_type_id": "vaal_axe",
      "name": "Bloodthirsty Vaal Axe",
      "base_name": "Vaal Axe",
      "class": "two_hand_axe",
      "rarity": "rare",
      "tags": [],
      "requirements": { "level": 25, "strength": 50, "dexterity": 0, "intelligence": 0 },
      "implicit": null,
      "prefixes": [
        { "affix_id": "added_phys", "name": "Merciless", "stat": "added_physical_damage", "scope": "local", "tier": 3, "value": 40, "value_max": 50, "tier_min": 40, "tier_max": 50, "tier_max_value": [40, 50] },
        { "affix_id": "inc_phys", "name": "Tyrannical", "stat": "increased_physical_damage", "scope": "local", "tier": 3, "value": 120, "tier_min": 100, "tier_max": 140 }
      ],
      "suffixes": [
        { "affix_id": "life_leech", "name": "of Leeching", "stat": "life_leech", "scope": "global", "tier": 1, "value": 3, "tier_min": 2, "tier_max": 4 }
      ],
      "defenses": { "armour": null, "evasion": null, "energy_shield": null },
      "damage": { "damages": [{ "damage_type": "physical", "min": 80, "max": 160 }], "attack_speed": 1.0, "critical_chance": 5.0, "spell_efficiency": 0.0 }
    },
    {
      "base_type_id": "jade_hatchet",
      "name": "Nimble Jade Hatchet",
      "base_name": "Jade Hatchet",
      "class": "one_hand_axe",
      "rarity": "magic",
      "tags": [],
      "requirements": { "level": 5, "strength": 10, "dexterity": 10, "intelligence": 0 },
      "implicit": null,
      "prefixes": [
        { "affix_id": "added_phys", "name": "Gleaming", "stat": "added_physical_damage", "scope": "local", "tier": 1, "value": 8, "value_max": 15, "tier_min": 8, "tier_max": 15, "tier_max_value": [8, 15] }
      ],
      "suffixes": [
        { "affix_id": "attack_speed", "name": "of Alacrity", "stat": "increased_attack_speed", "scope": "global", "tier": 2, "value": 12, "tier_min": 10, "tier_max": 15 }
      ],
      "defenses": { "armour": null, "evasion": null, "energy_shield": null },
      "damage": { "damages": [{ "damage_type": "physical", "min": 25, "max": 50 }], "attack_speed": 1.4, "critical_chance": 5.0, "spell_efficiency": 0.0 }
    },
    {
      "base_type_id": "assassin_dagger",
      "name": "Venomous Assassin Dagger",
      "base_name": "Assassin Dagger",
      "class": "dagger",
      "rarity": "rare",
      "tags": [],
      "requirements": { "level": 15, "strength": 0, "dexterity": 30, "intelligence": 0 },
      "implicit": { "affix_id": "crit_implicit", "name": "Critical", "stat": "increased_critical_chance", "scope": "global", "tier": 2, "value": 40, "tier_min": 35, "tier_max": 45 },
      "prefixes": [
        { "affix_id": "added_phys", "name": "Wicked", "stat": "added_physical_damage", "scope": "local", "tier": 2, "value": 15, "value_max": 22, "tier_min": 15, "tier_max": 22, "tier_max_value": [15, 22] },
        { "affix_id": "added_chaos", "name": "Malicious", "stat": "added_chaos_damage", "scope": "local", "tier": 1, "value": 20, "value_max": 30, "tier_min": 20, "tier_max": 30, "tier_max_value": [20, 30] }
      ],
      "suffixes": [
        { "affix_id": "crit_multi", "name": "of Devastation", "stat": "increased_critical_damage", "scope": "global", "tier": 1, "value": 30, "tier_min": 25, "tier_max": 35 }
      ],
      "defenses": { "armour": null, "evasion": null, "energy_shield": null },
      "damage": { "damages": [{ "damage_type": "physical", "min": 20, "max": 45 }], "attack_speed": 1.5, "critical_chance": 8.0, "spell_efficiency": 0.0 }
    },
    {
      "base_type_id": "maraketh_bow",
      "name": "Swift Maraketh Bow",
      "base_name": "Maraketh Bow",
      "class": "bow",
      "rarity": "rare",
      "tags": [],
      "requirements": { "level": 20, "strength": 0, "dexterity": 40, "intelligence": 0 },
      "implicit": { "affix_id": "move_implicit", "name": "Movement", "stat": "increased_movement_speed", "scope": "global", "tier": 1, "value": 10, "tier_min": 8, "tier_max": 12 },
      "prefixes": [
        { "affix_id": "added_phys", "name": "Vicious", "stat": "added_physical_damage", "scope": "local", "tier": 2, "value": 25, "value_max": 35, "tier_min": 25, "tier_max": 35, "tier_max_value": [25, 35] },
        { "affix_id": "added_cold", "name": "Frozen", "stat": "added_cold_damage", "scope": "local", "tier": 1, "value": 15, "value_max": 25, "tier_min": 15, "tier_max": 25, "tier_max_value": [15, 25] }
      ],
      "suffixes": [
        { "affix_id": "attack_speed", "name": "of the Wind", "stat": "increased_attack_speed", "scope": "global", "tier": 2, "value": 12, "tier_min": 10, "tier_max": 15 },
        { "affix_id": "accuracy", "name": "of the Ranger", "stat": "added_accuracy", "scope": "global", "tier": 1, "value": 150, "tier_min": 120, "tier_max": 180 }
      ],
      "defenses": { "armour": null, "evasion": null, "energy_shield": null },
      "damage": { "damages": [{ "damage_type": "physical", "min": 35, "max": 90 }], "attack_speed": 1.4, "critical_chance": 6.5, "spell_efficiency": 0.0 }
    },
    {
      "base_type_id": "fire_wand",
      "name": "Blazing Fire Wand",
      "base_name": "Fire Wand",
      "class": "wand",
      "rarity": "rare",
      "tags": [],
      "requirements": { "level": 15, "strength": 0, "dexterity": 0, "intelligence": 30 },
      "implicit": { "affix_id": "fire_implicit", "name": "Fire Damage", "stat": "added_fire_damage", "scope": "local", "tier": 1, "value": 15, "value_max": 25, "tier_min": 15, "tier_max": 25, "tier_max_value": [15, 25] },
      "prefixes": [
        { "affix_id": "elem_dmg", "name": "Arcane", "stat": "increased_elemental_damage", "scope": "global", "tier": 2, "value": 50, "tier_min": 40, "tier_max": 60 },
        { "affix_id": "fire_dmg", "name": "Burning", "stat": "increased_elemental_damage", "scope": "global", "tier": 2, "value": 40, "tier_min": 35, "tier_max": 45 }
      ],
      "suffixes": [
        { "affix_id": "attack_speed", "name": "of Flames", "stat": "increased_attack_speed", "scope": "global", "tier": 1, "value": 12, "tier_min": 10, "tier_max": 15 }
      ],
      "defenses": { "armour": null, "evasion": null, "energy_shield": null },
      "damage": { "damages": [{ "damage_type": "fire", "min": 15, "max": 35 }], "attack_speed": 1.4, "critical_chance": 8.0, "spell_efficiency": 1.0 }
    },
    {
      "base_type_id": "eclipse_staff",
      "name": "Eldritch Eclipse Staff",
      "base_name": "Eclipse Staff",
      "class": "staff",
      "rarity": "rare",
      "tags": [],
      "requirements": { "level": 30, "strength": 0, "dexterity": 0, "intelligence": 60 },
      "implicit": { "affix_id": "armour_implicit", "name": "Armour", "stat": "added_armour", "scope": "global", "tier": 1, "value": 50, "tier_min": 40, "tier_max": 60 },
      "prefixes": [
        { "affix_id": "elem_dmg", "name": "Runic", "stat": "increased_elemental_damage", "scope": "global", "tier": 3, "value": 80, "tier_min": 70, "tier_max": 90 },
        { "affix_id": "added_light", "name": "Crackling", "stat": "added_lightning_damage", "scope": "local", "tier": 2, "value": 5, "value_max": 40, "tier_min": 5, "tier_max": 40, "tier_max_value": [5, 40] }
      ],
      "suffixes": [
        { "affix_id": "attack_speed", "name": "of Wizardry", "stat": "increased_attack_speed", "scope": "global", "tier": 2, "value": 18, "tier_min": 15, "tier_max": 22 },
        { "affix_id": "mana", "name": "of the Sage", "stat": "added_mana", "scope": "global", "tier": 2, "value": 60, "tier_min": 50, "tier_max": 70 }
      ],
      "defenses": { "armour": null, "evasion": null, "energy_shield": null },
      "damage": { "damages": [{ "damage_type": "physical", "min": 40, "max": 80 }], "attack_speed": 1.1, "critical_chance": 7.0, "spell_efficiency": 1.2 }
    },
    {
      "base_type_id": "iron_plate",
      "name": "Sturdy Iron Plate",
      "base_name": "Iron Plate",
      "class": "body_armour",
      "rarity": "magic",
      "tags": [],
      "requirements": { "level": 1, "strength": 10, "dexterity": 0, "intelligence": 0 },
      "implicit": null,
      "prefixes": [
        { "affix_id": "life", "name": "Stout", "stat": "added_life", "scope": "global", "tier": 1, "value": 40, "tier_min": 30, "tier_max": 50 }
      ],
      "suffixes": [
        { "affix_id": "fire_res", "name": "of the Salamander", "stat": "fire_resistance", "scope": "global", "tier": 1, "value": 20, "tier_min": 15, "tier_max": 25 }
      ],
      "defenses": { "armour": 150, "evasion": null, "energy_shield": null },
      "damage": null
    },
    {
      "base_type_id": "steel_plate",
      "name": "Warlord's Steel Plate",
      "base_name": "Steel Plate",
      "class": "body_armour",
      "rarity": "rare",
      "tags": [],
      "requirements": { "level": 20, "strength": 40, "dexterity": 0, "intelligence": 0 },
      "implicit": null,
      "prefixes": [
        { "affix_id": "life", "name": "Vigorous", "stat": "added_life", "scope": "global", "tier": 2, "value": 80, "tier_min": 70, "tier_max": 90 },
        { "affix_id": "armour", "name": "Reinforced", "stat": "added_armour", "scope": "global", "tier": 2, "value": 100, "tier_min": 80, "tier_max": 120 }
      ],
      "suffixes": [
        { "affix_id": "fire_res", "name": "of the Dragon", "stat": "fire_resistance", "scope": "global", "tier": 2, "value": 35, "tier_min": 30, "tier_max": 40 },
        { "affix_id": "cold_res", "name": "of the Yeti", "stat": "cold_resistance", "scope": "global", "tier": 2, "value": 35, "tier_min": 30, "tier_max": 40 }
      ],
      "defenses": { "armour": 280, "evasion": null, "energy_shield": null },
      "damage": null
    },
    {
      "base_type_id": "leather_vest",
      "name": "Shadow Leather Vest",
      "base_name": "Leather Vest",
      "class": "body_armour",
      "rarity": "rare",
      "tags": [],
      "requirements": { "level": 10, "strength": 0, "dexterity": 25, "intelligence": 0 },
      "implicit": null,
      "prefixes": [
        { "affix_id": "life", "name": "Healthy", "stat": "added_life", "scope": "global", "tier": 1, "value": 50, "tier_min": 40, "tier_max": 60 },
        { "affix_id": "evasion", "name": "Shadowy", "stat": "added_evasion", "scope": "global", "tier": 2, "value": 150, "tier_min": 120, "tier_max": 180 }
      ],
      "suffixes": [
        { "affix_id": "move_speed", "name": "of the Wind", "stat": "increased_movement_speed", "scope": "global", "tier": 1, "value": 10, "tier_min": 8, "tier_max": 12 }
      ],
      "defenses": { "armour": null, "evasion": 200, "energy_shield": null },
      "damage": null
    },
    {
      "base_type_id": "iron_helm",
      "name": "Reinforced Iron Helm",
      "base_name": "Iron Helm",
      "class": "helmet",
      "rarity": "magic",
      "tags": [],
      "requirements": { "level": 1, "strength": 0, "dexterity": 0, "intelligence": 0 },
      "implicit": null,
      "prefixes": [
        { "affix_id": "life", "name": "Hale", "stat": "added_life", "scope": "global", "tier": 1, "value": 25, "tier_min": 20, "tier_max": 30 }
      ],
      "suffixes": [
        { "affix_id": "cold_res", "name": "of the Walrus", "stat": "cold_resistance", "scope": "global", "tier": 1, "value": 18, "tier_min": 15, "tier_max": 22 }
      ],
      "defenses": { "armour": 80, "evasion": null, "energy_shield": null },
      "damage": null
    },
    {
      "base_type_id": "gold_ring",
      "name": "Ruby Gold Ring",
      "base_name": "Gold Ring",
      "class": "ring",
      "rarity": "magic",
      "tags": [],
      "requirements": { "level": 1, "strength": 0, "dexterity": 0, "intelligence": 0 },
      "implicit": { "affix_id": "rarity_implicit", "name": "Rarity", "stat": "increased_item_rarity", "scope": "global", "tier": 1, "value": 10, "tier_min": 8, "tier_max": 12 },
      "prefixes": [
        { "affix_id": "life", "name": "Healthy", "stat": "added_life", "scope": "global", "tier": 1, "value": 30, "tier_min": 25, "tier_max": 35 }
      ],
      "suffixes": [
        { "affix_id": "fire_res", "name": "of the Salamander", "stat": "fire_resistance", "scope": "global", "tier": 1, "value": 25, "tier_min": 20, "tier_max": 30 },
        { "affix_id": "light_res", "name": "of Grounding", "stat": "lightning_resistance", "scope": "global", "tier": 1, "value": 15, "tier_min": 12, "tier_max": 18 }
      ],
      "defenses": { "armour": null, "evasion": null, "energy_shield": null },
      "damage": null
    },
    {
      "base_type_id": "iron_gauntlets",
      "name": "Spiked Iron Gauntlets",
      "base_name": "Iron Gauntlets",
      "class": "gloves",
      "rarity": "magic",
      "tags": [],
      "requirements": { "level": 5, "strength": 15, "dexterity": 0, "intelligence": 0 },
      "implicit": null,
      "prefixes": [
        { "affix_id": "added_phys", "name": "Heavy", "stat": "added_physical_damage", "scope": "global", "tier": 1, "value": 5, "value_max": 10, "tier_min": 5, "tier_max": 10, "tier_max_value": [5, 10] }
      ],
      "suffixes": [
        { "affix_id": "attack_speed", "name": "of Speed", "stat": "increased_attack_speed", "scope": "global", "tier": 1, "value": 6, "tier_min": 4, "tier_max": 8 }
      ],
      "defenses": { "armour": 45, "evasion": null, "energy_shield": null },
      "damage": null
    },
    {
      "base_type_id": "iron_boots",
      "name": "Traveler's Iron Boots",
      "base_name": "Iron Boots",
      "class": "boots",
      "rarity": "magic",
      "tags": [],
      "requirements": { "level": 5, "strength": 10, "dexterity": 0, "intelligence": 0 },
      "implicit": null,
      "prefixes": [
        { "affix_id": "life", "name": "Stout", "stat": "added_life", "scope": "global", "tier": 1, "value": 35, "tier_min": 30, "tier_max": 40 }
      ],
      "suffixes": [
        { "affix_id": "move_speed", "name": "of the Ox", "stat": "increased_movement_speed", "scope": "global", "tier": 1, "value": 15, "tier_min": 12, "tier_max": 18 }
      ],
      "defenses": { "armour": 50, "evasion": null, "energy_shield": null },
      "damage": null
    },
    {
      "base_type_id": "gold_amulet",
      "name": "Empowering Gold Amulet",
      "base_name": "Gold Amulet",
      "class": "amulet",
      "rarity": "rare",
      "tags": [],
      "requirements": { "level": 10, "strength": 0, "dexterity": 0, "intelligence": 0 },
      "implicit": { "affix_id": "rarity_implicit", "name": "Rarity", "stat": "increased_item_rarity", "scope": "global", "tier": 1, "value": 15, "tier_min": 12, "tier_max": 18 },
      "prefixes": [
        { "affix_id": "life", "name": "Rotund", "stat": "added_life", "scope": "global", "tier": 2, "value": 55, "tier_min": 45, "tier_max": 65 },
        { "affix_id": "phys_dmg", "name": "Warrior's", "stat": "increased_physical_damage", "scope": "global", "tier": 1, "value": 25, "tier_min": 20, "tier_max": 30 }
      ],
      "suffixes": [
        { "affix_id": "accuracy", "name": "of Precision", "stat": "added_accuracy", "scope": "global", "tier": 1, "value": 100, "tier_min": 80, "tier_max": 120 }
      ],
      "defenses": { "armour": null, "evasion": null, "energy_shield": null },
      "damage": null
    },
    {
      "base_type_id": "leather_belt",
      "name": "Hunter's Leather Belt",
      "base_name": "Leather Belt",
      "class": "belt",
      "rarity": "magic",
      "tags": [],
      "requirements": { "level": 1, "strength": 0, "dexterity": 0, "intelligence": 0 },
      "implicit": { "affix_id": "life_implicit", "name": "Life", "stat": "added_life", "scope": "global", "tier": 1, "value": 30, "tier_min": 25, "tier_max": 35 },
      "prefixes": [
        { "affix_id": "life", "name": "Stout", "stat": "added_life", "scope": "global", "tier": 1, "value": 40, "tier_min": 35, "tier_max": 45 }
      ],
      "suffixes": [
        { "affix_id": "inc_life", "name": "of the Chemist", "stat": "increased_life", "scope": "global", "tier": 1, "value": 10, "tier_min": 8, "tier_max": 12 }
      ],
      "defenses": { "armour": null, "evasion": null, "energy_shield": null },
      "damage": null
    },
    {
      "base_type_id": "tower_shield",
      "name": "Guardian's Tower Shield",
      "base_name": "Tower Shield",
      "class": "shield",
      "rarity": "rare",
      "tags": [],
      "requirements": { "level": 15, "strength": 30, "dexterity": 0, "intelligence": 0 },
      "implicit": null,
      "prefixes": [
        { "affix_id": "life", "name": "Vigorous", "stat": "added_life", "scope": "global", "tier": 2, "value": 70, "tier_min": 60, "tier_max": 80 },
        { "affix_id": "armour", "name": "Plated", "stat": "added_armour", "scope": "global", "tier": 1, "value": 60, "tier_min": 50, "tier_max": 70 }
      ],
      "suffixes": [
        { "affix_id": "all_res", "name": "of Resistance", "stat": "all_resistances", "scope": "global", "tier": 1, "value": 10, "tier_min": 8, "tier_max": 12 }
      ],
      "defenses": { "armour": 180, "evasion": null, "energy_shield": null },
      "damage": null
    },
    {
      "base_type_id": "venom_dagger",
      "name": "Viper's Fang",
      "base_name": "Venom Dagger",
      "class": "dagger",
      "rarity": "rare",
      "tags": [],
      "requirements": { "level": 15, "strength": 0, "dexterity": 25, "intelligence": 10 },
      "implicit": { "affix_id": "crit_implicit", "name": "Critical", "stat": "increased_critical_chance", "scope": "global", "tier": 1, "value": 30, "tier_min": 25, "tier_max": 35 },
      "prefixes": [
        { "affix_id": "added_chaos", "name": "Toxic", "stat": "added_chaos_damage", "scope": "local", "tier": 2, "value": 30, "value_max": 45, "tier_min": 30, "tier_max": 45, "tier_max_value": [30, 45] },
        { "affix_id": "poison_conv", "name": "Venomous", "stat": "convert_physical_to_poison", "scope": "global", "tier": 2, "value": 40, "tier_min": 35, "tier_max": 50 }
      ],
      "suffixes": [
        { "affix_id": "poison_dur", "name": "of Lingering", "stat": "increased_poison_duration", "scope": "global", "tier": 1, "value": 30, "tier_min": 25, "tier_max": 40 },
        { "affix_id": "attack_speed", "name": "of the Adder", "stat": "increased_attack_speed", "scope": "global", "tier": 1, "value": 10, "tier_min": 8, "tier_max": 12 }
      ],
      "defenses": { "armour": null, "evasion": null, "energy_shield": null },
      "damage": { "damages": [{ "damage_type": "physical", "min": 25, "max": 55 }, { "damage_type": "chaos", "min": 10, "max": 25 }], "attack_speed": 1.5, "critical_chance": 7.5, "spell_efficiency": 0.0 }
    },
    {
      "base_type_id": "bleed_axe",
      "name": "Bloodletter's Cleaver",
      "base_name": "Rusted Cleaver",
      "class": "one_hand_axe",
      "rarity": "rare",
      "tags": [],
      "requirements": { "level": 20, "strength": 35, "dexterity": 15, "intelligence": 0 },
      "implicit": null,
      "prefixes": [
        { "affix_id": "added_phys", "name": "Cruel", "stat": "added_physical_damage", "scope": "local", "tier": 2, "value": 25, "value_max": 35, "tier_min": 25, "tier_max": 35, "tier_max_value": [25, 35] },
        { "affix_id": "bleed_conv", "name": "Bloodthirsty", "stat": "convert_physical_to_bleed", "scope": "global", "tier": 2, "value": 50, "tier_min": 40, "tier_max": 60 }
      ],
      "suffixes": [
        { "affix_id": "bleed_dur", "name": "of Hemorrhage", "stat": "increased_bleed_duration", "scope": "global", "tier": 1, "value": 40, "tier_min": 30, "tier_max": 50 },
        { "affix_id": "bleed_mag", "name": "of Exsanguination", "stat": "bleed_magnitude", "scope": "global", "tier": 1, "value": 25, "tier_min": 20, "tier_max": 30 }
      ],
      "defenses": { "armour": null, "evasion": null, "energy_shield": null },
      "damage": { "damages": [{ "damage_type": "physical", "min": 40, "max": 80 }], "attack_speed": 1.3, "critical_chance": 5.0, "spell_efficiency": 0.0 }
    },
    {
      "base_type_id": "burn_sceptre",
      "name": "Pyroclast Sceptre",
      "base_name": "Ritual Sceptre",
      "class": "wand",
      "rarity": "rare",
      "tags": [],
      "requirements": { "level": 25, "strength": 10, "dexterity": 0, "intelligence": 40 },
      "implicit": { "affix_id": "elem_implicit", "name": "Elemental", "stat": "increased_elemental_damage", "scope": "global", "tier": 1, "value": 15, "tier_min": 12, "tier_max": 20 },
      "prefixes": [
        { "affix_id": "added_fire", "name": "Scorching", "stat": "added_fire_damage", "scope": "local", "tier": 2, "value": 35, "value_max": 50, "tier_min": 35, "tier_max": 50, "tier_max_value": [35, 50] },
        { "affix_id": "burn_conv", "name": "Igniting", "stat": "convert_fire_to_burn", "scope": "global", "tier": 2, "value": 60, "tier_min": 50, "tier_max": 70 }
      ],
      "suffixes": [
        { "affix_id": "burn_dur", "name": "of Conflagration", "stat": "increased_burn_duration", "scope": "global", "tier": 1, "value": 50, "tier_min": 40, "tier_max": 60 },
        { "affix_id": "burn_mag", "name": "of Immolation", "stat": "burn_magnitude", "scope": "global", "tier": 1, "value": 35, "tier_min": 30, "tier_max": 45 }
      ],
      "defenses": { "armour": null, "evasion": null, "energy_shield": null },
      "damage": { "damages": [{ "damage_type": "fire", "min": 30, "max": 55 }], "attack_speed": 1.2, "critical_chance": 7.0, "spell_efficiency": 1.0 }
    },
    {
      "base_type_id": "freeze_staff",
      "name": "Frostbound Staff",
      "base_name": "Frozen Staff",
      "class": "staff",
      "rarity": "rare",
      "tags": [],
      "requirements": { "level": 30, "strength": 0, "dexterity": 0, "intelligence": 55 },
      "implicit": { "affix_id": "armour_implicit", "name": "Block", "stat": "added_armour", "scope": "global", "tier": 1, "value": 40, "tier_min": 35, "tier_max": 50 },
      "prefixes": [
        { "affix_id": "added_cold", "name": "Glacial", "stat": "added_cold_damage", "scope": "local", "tier": 3, "value": 50, "value_max": 65, "tier_min": 50, "tier_max": 65, "tier_max_value": [50, 65] },
        { "affix_id": "freeze_conv", "name": "Freezing", "stat": "convert_cold_to_freeze", "scope": "global", "tier": 2, "value": 45, "tier_min": 40, "tier_max": 55 }
      ],
      "suffixes": [
        { "affix_id": "freeze_dur", "name": "of the Glacier", "stat": "increased_freeze_duration", "scope": "global", "tier": 1, "value": 60, "tier_min": 50, "tier_max": 75 },
        { "affix_id": "chill_conv", "name": "of Chilling", "stat": "convert_cold_to_chill", "scope": "global", "tier": 1, "value": 35, "tier_min": 30, "tier_max": 45 }
      ],
      "defenses": { "armour": null, "evasion": null, "energy_shield": null },
      "damage": { "damages": [{ "damage_type": "cold", "min": 50, "max": 90 }], "attack_speed": 1.1, "critical_chance": 6.0, "spell_efficiency": 1.2 }
    },
    {
      "base_type_id": "static_bow",
      "name": "Stormcaller's Longbow",
      "base_name": "Recurve Bow",
      "class": "bow",
      "rarity": "rare",
      "tags": [],
      "requirements": { "level": 25, "strength": 0, "dexterity": 45, "intelligence": 15 },
      "implicit": { "affix_id": "move_implicit", "name": "Movement", "stat": "increased_movement_speed", "scope": "global", "tier": 1, "value": 8, "tier_min": 6, "tier_max": 10 },
      "prefixes": [
        { "affix_id": "added_light", "name": "Shocking", "stat": "added_lightning_damage", "scope": "local", "tier": 2, "value": 5, "value_max": 60, "tier_min": 5, "tier_max": 60, "tier_max_value": [5, 60] },
        { "affix_id": "static_conv", "name": "Electrifying", "stat": "convert_lightning_to_static", "scope": "global", "tier": 2, "value": 55, "tier_min": 45, "tier_max": 65 }
      ],
      "suffixes": [
        { "affix_id": "static_dur", "name": "of Thunder", "stat": "increased_static_duration", "scope": "global", "tier": 1, "value": 45, "tier_min": 35, "tier_max": 55 },
        { "affix_id": "attack_speed", "name": "of Lightning", "stat": "increased_attack_speed", "scope": "global", "tier": 2, "value": 15, "tier_min": 12, "tier_max": 18 }
      ],
      "defenses": { "armour": null, "evasion": null, "energy_shield": null },
      "damage": { "damages": [{ "damage_type": "physical", "min": 30, "max": 70 }, { "damage_type": "lightning", "min": 15, "max": 45 }], "attack_speed": 1.35, "critical_chance": 6.0, "spell_efficiency": 0.0 }
    },
    {
      "base_type_id": "fear_claw",
      "name": "Terrorfiend Claw",
      "base_name": "Shadow Claw",
      "class": "claw",
      "rarity": "rare",
      "tags": [],
      "requirements": { "level": 20, "strength": 10, "dexterity": 35, "intelligence": 10 },
      "implicit": { "affix_id": "leech_implicit", "name": "Life Leech", "stat": "life_leech", "scope": "global", "tier": 1, "value": 2, "tier_min": 1, "tier_max": 3 },
      "prefixes": [
        { "affix_id": "added_chaos", "name": "Nightmarish", "stat": "added_chaos_damage", "scope": "local", "tier": 2, "value": 25, "value_max": 40, "tier_min": 25, "tier_max": 40, "tier_max_value": [25, 40] },
        { "affix_id": "fear_conv", "name": "Terrifying", "stat": "convert_chaos_to_fear", "scope": "global", "tier": 2, "value": 50, "tier_min": 40, "tier_max": 60 }
      ],
      "suffixes": [
        { "affix_id": "fear_dur", "name": "of Nightmares", "stat": "increased_fear_duration", "scope": "global", "tier": 1, "value": 40, "tier_min": 30, "tier_max": 50 },
        { "affix_id": "fear_mag", "name": "of Horror", "stat": "fear_magnitude", "scope": "global", "tier": 1, "value": 30, "tier_min": 25, "tier_max": 40 }
      ],
      "defenses": { "armour": null, "evasion": null, "energy_shield": null },
      "damage": { "damages": [{ "damage_type": "physical", "min": 25, "max": 50 }, { "damage_type": "chaos", "min": 15, "max": 35 }], "attack_speed": 1.5, "critical_chance": 6.5, "spell_efficiency": 0.0 }
    },
    {
      "base_type_id": "slow_mace",
      "name": "Timewarden's Mace",
      "base_name": "War Hammer",
      "class": "one_hand_mace",
      "rarity": "rare",
      "tags": [],
      "requirements": { "level": 25, "strength": 45, "dexterity": 0, "intelligence": 0 },
      "implicit": null,
      "prefixes": [
        { "affix_id": "added_phys", "name": "Brutal", "stat": "added_physical_damage", "scope": "local", "tier": 2, "value": 30, "value_max": 45, "tier_min": 30, "tier_max": 45, "tier_max_value": [30, 45] },
        { "affix_id": "slow_conv", "name": "Slowing", "stat": "convert_physical_to_slow", "scope": "global", "tier": 2, "value": 45, "tier_min": 35, "tier_max": 55 }
      ],
      "suffixes": [
        { "affix_id": "slow_dur", "name": "of Lethargy", "stat": "increased_slow_duration", "scope": "global", "tier": 1, "value": 50, "tier_min": 40, "tier_max": 60 },
        { "affix_id": "slow_mag", "name": "of Hindrance", "stat": "slow_magnitude", "scope": "global", "tier": 1, "value": 35, "tier_min": 30, "tier_max": 45 }
      ],
      "defenses": { "armour": null, "evasion": null, "energy_shield": null },
      "damage": { "damages": [{ "damage_type": "physical", "min": 55, "max": 95 }], "attack_speed": 1.1, "critical_chance": 5.0, "spell_efficiency": 0.0 }
    }
  ]
}
